hot_restart.py
hot_restart-0.2.4.dist-info/LICENSE
hot_restart-0.2.4.dist-info/WHEEL
hot_restart-0.2.4.dist-info/METADATA
hot_restart-0.2.4.dist-info/RECORD
